{
  "kind": "collectionType",
  "collectionName": "career_forms",
  "info": {
    "singularName": "career-form",
    "pluralName": "career-forms",
    "displayName": "CareerForm",
    "description": ""
  },
  "options": {
    "draftAndPublish": true
  },
  "pluginOptions": {},
  "attributes": {
    "FirstName": {
      "type": "string"
    },
    "LastName": {
      "type": "string"
    },
    "Email": {
      "type": "email"
    },
    "ContactNumber": {
      "type": "string"
    },
    "Resume": {
      "type": "media",
      "multiple": false,
      "required": false,
      "allowedTypes": [
        "images",
        "files",
        "videos",
        "audios"
      ]
    },
    "TermsAccepted": {
      "type": "boolean"
    }
  }
}
